{
  "client_id": "CA_006",
  "metadata": {
    "date_conversation": "2026-01-10",
    "duration": "30 min",
    "language": "Espagnol"
  },
  "identite": {
    "genre": "Homme",
    "statut_relationnel": "VIP"
  },
  "localisation": {
    "europe": [
      "Madrid"
    ]
  },
  "mobilite_rythme_vie": {
    "frequence_deplacement": "Mobile"
  },
  "lifestyle_centres_interet": {},
  "style_personnel": {
    "pieces_favorites": [
      "Sacs"
    ]
  },
  "projet_achat": {
    "motif": "Anniversaire",
    "budget": "25k+"
  },
  "appetence_evenementielle": {},
  "relation_produit_innovation": {},
  "reseau_influence": {
    "influence": "Réseau_affluent"
  },
  "suivi": {
    "action": "Rappeler",
    "echeance": "M+1",
    "canal_contact": "Email"
  },
  "metadata_client": {
    "regime_alimentaire": "Végane"
  }
}