{
  "client_id": "CA_352",
  "metadata": {
    "date_conversation": "2026-07-15",
    "duration": "43 min",
    "language": "Anglais",
    "profile_version": "2.0"
  },
  "identite": {
    "genre": "Femme",
    "statut_relationnel": "VIP",
    "langue_parlee": [
      "Français"
    ],
    "profession_secteur": {
      "Cadre_Manager": [],
      "Art_Creation": [
        "Artiste"
      ],
      "Tech_Digital": [
        "Ingénieur"
      ],
      "Medias_Communication": [
        "Marketing"
      ]
    }
  },
  "localisation": {
    "europe": [
      "Berlin"
    ]
  },
  "lifestyle_centres_interet": {
    "sport": {
      "collectif": [],
      "individuel": {
        "bien_etre": [
          "Yoga"
        ]
      }
    },
    "musique": {},
    "voyage": {
      "experience": [
        "Luxe"
      ]
    }
  },
  "style_personnel": {
    "couleurs_preferees": {
      "metalliques": [
        "Or"
      ]
    },
    "matieres_preferees": {
      "naturelles": [
        "Lin"
      ],
      "alternatives": [
        "Matières vegan"
      ]
    },
    "pieces_favorites": {
      "accessoires": [
        "Montres"
      ]
    }
  },
  "projet_achat": {
    "budget": "15–25k"
  },
  "preferences_contraintes": {
    "regime": [
      "Vegane"
    ]
  },
  "suivi": {
    "action": [
      "Rappeler"
    ],
    "echeance": "M+1",
    "canal_contact": "Email"
  }
}